greetings_helloworld2030/Listing18_1.py
greetings_helloworld2030/__init__.py
greetings_helloworld2030-1.0.0.dist-info/licenses/LICENSE
greetings_helloworld2030-1.0.0.dist-info/WHEEL
greetings_helloworld2030-1.0.0.dist-info/METADATA
greetings_helloworld2030-1.0.0.dist-info/RECORD
