Metadata-Version: 2.4
Name: greetings-helloworld2030
Version: 1.0.0
Summary: This is the greeting package, the simplest package in the Python World!
Author-email: Fabio Nelli <meccanismo.complesso@gmail.com>
License-Expression: MIT
License-File: LICENSE
Project-URL: Home, https://meccanismocomplesso.org
